README.md
setup.py
runthis/runthis-client.min.js
runthis/sphinxext.py
runthis_sphinxext.egg-info/PKG-INFO
runthis_sphinxext.egg-info/SOURCES.txt
runthis_sphinxext.egg-info/dependency_links.txt
runthis_sphinxext.egg-info/entry_points.txt
runthis_sphinxext.egg-info/not-zip-safe
runthis_sphinxext.egg-info/top_level.txt