Metadata-Version: 2.1
Name: runthis-sphinxext
Version: 0.0.3
Summary: Provides a sphinx code-block for rendering RunThis blocks
Home-page: https://github.com/regro/runthis-sphinxext
Author: Anthony Scopatz
Author-email: scopatz@gmail.com
Maintainer: Anthony Scopatz
License: BSD
Platform: Cross Platform
Classifier: Programming Language :: Python :: 3
Requires-Python: >=3.6
